gitfs2/__init__.py
gitfs2/_version.py
gitfs2/constants.py
gitfs2/opener.py
gitfs2/repo.py
gitfs2/reporter.py
gitfs2-0.0.5.dist-info/LICENSE
gitfs2-0.0.5.dist-info/METADATA
gitfs2-0.0.5.dist-info/WHEEL
gitfs2-0.0.5.dist-info/entry_points.txt
gitfs2-0.0.5.dist-info/top_level.txt
gitfs2-0.0.5.dist-info/RECORD
