Metadata-Version: 2.1
Name: gitfs2
Version: 0.0.5
Summary: Python file system 2 over GitPython
Home-page: https://github.com/moremoban/gitfs2
Download-URL: https://github.com/moremoban/gitfs2/archive/0.0.5.tar.gz
Author: C.W.
Author-email: wangc_2011@hotmail.com
License: MIT
Keywords: python
Classifier: Topic :: Software Development :: Libraries
Classifier: Programming Language :: Python
Classifier: Intended Audience :: Developers
Classifier: Programming Language :: Python :: 2.6
Classifier: Programming Language :: Python :: 2.7
Classifier: Programming Language :: Python :: 3.3
Classifier: Programming Language :: Python :: 3.4
Classifier: Programming Language :: Python :: 3.5
Classifier: Programming Language :: Python :: 3.6
Classifier: Programming Language :: Python :: 3.7
Classifier: Programming Language :: Python :: 3.8
License-File: LICENSE
Requires-Dist: fs
Requires-Dist: crayons
Requires-Dist: GitPython
Requires-Dist: git-url-parse>=1.2.2
